{"escapees":{"humans":{"1":{"name":"Bluezinho Albert","ckey":"bluezinho","location":"Emergency Shuttle","health":85.6956,"job":"Medical Doctor","species":"Lizardperson"},"2":{"name":"Francisco Leichter","ckey":"verillius","location":"Emergency Shuttle","health":-338.546,"job":"Shaft Miner","species":"Human"},"3":{"name":"Gragnir Grolob","ckey":"haggisshuu","location":"Emergency Shuttle","health":-19.82,"job":"Botanist","species":"Human"},"4":{"name":"Hartley Riggle","ckey":"tythesmonk","location":"Emergency Shuttle","health":-314.833,"job":"Roboticist","species":"Human"},"5":{"name":"Jack Heckler (as Jeffery Jefferson)","ckey":"jathomar","location":"CentCom Recovery Ship","health":100,"job":"Chaplain","species":"Human"},"6":{"name":"Julio Brandenburg","ckey":"doctormad","location":"Emergency Shuttle","health":-506.91,"job":"Roboticist","species":"Human"},"7":{"name":"Lukas Moberly","ckey":"adeptmechanicus","location":"Emergency Shuttle","health":-114.5,"job":"Assistant","species":"Human"},"8":{"name":"Osbert Leichter","ckey":"thoreaufare","location":"Emergency Shuttle","health":-377.5,"job":"Shaft Miner","species":"Human"},"9":{"name":"Taya Velvet","ckey":"datmanisdumb","location":"CentCom Recovery Ship","health":92,"job":"Medical Doctor","species":"Human"},"10":{"name":"Whittaker Rose","ckey":"cscottburgess","location":"Emergency Shuttle","health":-393.16,"job":"Station Engineer","species":"Human"}},"silicons":[],"others":{"1":{"name":"Kolton Rhinehart","ckey":"manmail","location":"CentCom Docks","health":100,"typepath":"/mob/living/brain"}},"npcs":{"Cayenne":1,"Medibot":2}},"abandoned":{"humans":{"1":{"name":"August White","ckey":"zorezore","location":"Space","health":13.8425,"job":"Geneticist","species":"Human"},"2":{"name":"Banana","ckey":"pandolphina","location":"the Unexplored Location","health":100,"job":"Lifebringer","species":"Podperson"},"3":{"name":"Fixes-The-Station","ckey":"re1taz","location":"the BMP Asteroid Level 1","health":-219.333,"job":"Unassigned","species":"Lizardperson"},"4":{"name":"Unknown","ckey":"saltyscabbard","location":"Prison Wing","health":-703.039,"job":"Cook","species":"Human"},"5":{"name":"Hal Linton","ckey":"re1taz","location":"the BMP Asteroid Level 1","health":-150,"job":"Unassigned","species":"Human"},"6":{"name":"Indrick Boreale","ckey":"papaputin","location":"Morgue","health":-102.25,"job":"Head of Personnel","species":"Human"},"7":{"name":"Jack Gray","ckey":"re1taz","location":"Kitchen","health":100,"job":"Captain","species":"Human"},"8":{"name":"Jeffery Jefferson","ckey":"jefferyjefferson","location":"Chapel","health":-100.208,"job":"Security Officer","species":"Human"},"9":{"name":"Kills-Station-Helper","ckey":"pudgems","location":"Arrival Shuttle Hallway","health":68,"job":"Medical Doctor","species":"Lizardperson"},"10":{"name":"Patch-The-Hull","ckey":"swindel","location":"the BMP Asteroid Level 1","health":74.375,"job":"Chief Engineer","species":"Lizardperson"},"11":{"name":"Sabella Moon","ckey":"kelesis","location":"Space","health":-536.436,"job":"Assistant","species":"Human"},"12":{"name":"Tania Fiddler","ckey":"floorwaxer2","location":"Space","health":-57.6667,"job":"Station Engineer","species":"Human"},"13":{"name":"Unknown","ckey":"mlggendalf","location":"Prison Wing","health":-557.869,"job":"Chief Medical Officer","species":"Human"},"14":{"name":"Unknown","ckey":"re1taz","location":"the BMP Asteroid Level 1","health":-466.81,"job":"Unassigned","species":"Human"},"15":{"name":"Unknown","ckey":"koffheat","location":"Strange Location","health":-395.4,"job":"Security Officer","species":"Human"},"16":{"name":"Unknown","ckey":"re12","location":"the BMP Asteroid Level 1","health":-415.353,"job":"Warden","species":"Human"},"17":{"name":"Unknown","ckey":"ddanik","location":"Lavaland Wastes","health":-535.887,"job":"Lifebringer","species":"Podperson"},"18":{"name":"Unknown","ckey":"ddanik","location":"the BMP Asteroid Level 2","health":-400,"job":"Skeleton","species":"Spooky Scary Skeleton"}},"silicons":{"1":{"name":"D.A.N.","ckey":"ddanik","location":"the BMP Asteroid Level 1","health":500},"2":{"name":"G.U.A.R.D.I.A.N.","ckey":"pandolphina","location":"the BMP Asteroid Level 1","health":-128,"module":"Engineering"}},"others":{"1":{"name":"goliath","ckey":"re1taz","location":"the BMP Asteroid Level 1","health":200,"typepath":"/mob/living/simple_animal/hostile/asteroid/goliath/beast/tendril"},"2":{"name":"hierophant","ckey":"re1taz","location":"Hierophant's Arena","health":2500,"typepath":"/mob/living/simple_animal/hostile/megafauna/hierophant"},"3":{"name":"orange baby slime (946)","ckey":"saltyscabbard","location":"Dormitories","health":0,"typepath":"/mob/living/simple_animal/slime"}},"npcs":{"Unknown":16,"ancient goliath":2,"Angry Stick Dog":8,"Angry Stick Man":20,"basilisk":8,"basilisk den":2,"blood-drunk miner":1,"bone pit":8,"bubblegum":1,"butterfly":14,"Cleanbot":4,"Space Bat":9,"dwarf legion":3,"creature":10,"Floorbot":1,"giant spider":13,"goldgrub":10,"goliath":44,"goliath den":1,"gondola":8,"grey baby slime (123)":3,"Medibot":2,"hivelord":11,"hivelord den":3,"Ian":1,"brain":1,"Legion":1,"legion":16,"Mjor the Creative":1,"monkey":10,"mouse":3,"MULEbot":2,"nanotrasen minebot":2,"necropolis tendril":4,"Mysterious Medibot":1,"Officer Beep O'sky":2,"Officer Pingsky":1,"Paperwork":1,"goat":1,"Poly":1,"queen bee":2,"reanimated skeleton":123,"Runtime":1,"Pun Pun":1,"ghost":2,"Lizard":1,"watcher":26,"wumborian fugu":1}},"ghosts":{"name":"Osbert Leichter","ckey":"thoreaufare"},"additional data":{"station integrity":99.2}}
