{"escapees":{"humans":{"1":{"name":"Bumps","ckey":"boxxybooty","location":"Emergency Shuttle","health":100,"job":"Chief Engineer","species":"Mothmen"},"2":{"name":"Hana Robusto","ckey":"chippedice","location":"Emergency Shuttle","health":97,"job":"Curator","species":"Human"},"3":{"name":"Perna Landys","ckey":"ceanox","location":"Emergency Shuttle","health":95.7,"job":"Head of Security","species":"Human"},"4":{"name":"Rose White","ckey":"bobcat49","location":"Emergency Shuttle","health":98.1,"job":"Roboticist","species":"Human"},"5":{"name":"Sona Haku","ckey":"catmanpop","location":"Emergency Shuttle","health":96.7,"job":"Assistant","species":"Human"}},"silicons":[],"others":{"1":{"name":"scrawny tarantula (208)","ckey":"bigpenorboi","location":"Abandoned Ship Engine","health":0,"name":"scrawny tarantula (208)","typepath":"/mob/living/simple_animal/hostile/poison/giant_spider/tarantula"},"2":{"name":"Lara Black","ckey":"bilary","location":"Emergency Shuttle","health":100,"name":"Lara Black","typepath":"/mob/living/brain"}},"npcs":{"Cayenne":1,"chicken":1,"cow":1,"Medibot":5,"giant spider":4}},"abandoned":{"humans":{"1":{"name":"Andrea Focell","ckey":"thegoodgoo","location":"Transfer Centre","health":-105.5,"job":"Captain","species":"Human"},"2":{"name":"Connor Brooks","ckey":"x1pr0","location":"Transfer Centre","health":-104.3,"job":"Roboticist","species":"Human"},"3":{"name":"Flick Siegrist","ckey":"mlgdatboiwew","location":"the Unexplored Location","health":-695.6,"job":"Translocated Vet","species":"Human"},"4":{"name":"Dan Ox","ckey":"goodieboy","location":"Transfer Centre","health":-102.6,"job":"Botanist","species":"Human"},"5":{"name":"Unknown","ckey":"goodieboy","location":"Lavaland Wastes","health":-460.5,"job":"Hermit","species":"Human"},"6":{"name":"Loves-To-Absorb","ckey":"mlgdatboiwew","location":"Lavaland Wastes","health":-833.3,"job":"Translocated Vet","species":"Angel"},"7":{"name":"Amiyah McDonald","ckey":"jaedo","location":"Escape Shuttle Hallway","health":100,"job":"Cook","species":"Human"}},"silicons":[],"others":[],"npcs":{"Unknown":29,"alien drone":7,"alien hunter":4,"alien empress":1,"alien sentinel":4,"ash drake":2,"basilisk":18,"blank body":9,"butterfly":8,"Cleanbot":5,"ice skeleton":19,"creature":9,"dwarf legion":2,"Medibot":4,"Floorbot":2,"giant ice spider":8,"goldgrub":4,"goliath":31,"gondola":8,"grey baby slime (123)":2,"hierophant":1,"hivebot":86,"Ian":1,"ghost":1,"Legion":4,"legion":16,"Lizard":2,"mi-go":7,"monkey":10,"mouse":1,"MULEbot":2,"necropolis tendril":4,"netherworld link":4,"Mysterious Medibot":1,"Officer Beep O'sky":2,"Officer Pingsky":1,"Paperwork":1,"goat":1,"Poly":1,"Runtime":1,"shambling miner":9,"space carp":7,"space polar bear":16,"Spaceman":3,"strong hivebot":19,"Syndicate Operative":1,"Tom":1,"undead eskimo":11,"undead templar":10,"watcher":26,"midwife":1,"Inactive Camera Eye":1}},"ghosts":{"1":{"name":"Andrea Focell","ckey":"thegoodgoo"},"2":{"name":"scrawny tarantula (208)","ckey":"bigpenorboi"},"3":{"name":"Sentient Disease","ckey":"bilary"},"4":{"name":"Wisdom Rosensteel","ckey":"mlgdatboiwew"}},"additional data":{"station integrity":100}}
