{"escapees":{"humans":{"1":{"name":"Ark Shaffer","ckey":"runian","location":"Emergency Shuttle","health":86,"job":"Captain","species":"Human"},"2":{"name":"Marissa Smirnov","ckey":"hollytree","location":"Emergency Shuttle","health":80,"job":"Cook","species":"Human"},"3":{"name":"Melvin Enderly","ckey":"maciekbaki","location":"Emergency Shuttle","health":53,"job":"Atmospheric Technician","species":"Human"},"4":{"name":"Ryan Stalh","ckey":"superturtle41","location":"Emergency Shuttle","health":63.7,"job":"Research Director","species":"Human"},"5":{"name":"Sage Stewart","ckey":"rabidsquirrel10","location":"Emergency Shuttle","health":86,"job":"Scientist","species":"Human"},"6":{"name":"U-Mos","ckey":"skullheadjack","location":"Emergency Shuttle","health":82,"job":"Scientist","species":"Mothmen"},"7":{"name":"Vivian Prescott","ckey":"phenvalentia","location":"Emergency Shuttle","health":98.13,"job":"Curator","species":"Human"}},"silicons":{"1":{"name":"November","ckey":"cscottburgess","location":"Emergency Shuttle","health":500},"2":{"name":"Ro-Man","ckey":"hexob","location":"Emergency Shuttle","health":-100,"module":"pAI","module":"pAI"}},"others":[],"npcs":{"Cayenne":1,"Medibot":2}},"abandoned":{"humans":{"1":{"name":"Adolph Mills","ckey":"brhunter45","location":"Medbay Treatment Center","health":100,"job":"Chief Medical Officer","species":"Human"},"2":{"name":"Baum-Mobareed","ckey":"dnexus","location":"Morgue","health":-130,"job":"Botanist","species":"Lizardperson"},"3":{"name":"Epiphyas","ckey":"silentnoob57","location":"Security Office","health":43,"job":"Security Officer","species":"Mothmen"},"4":{"name":"Pepper","ckey":"dnexus","location":"the Unexplored Location","health":100,"job":"Lifebringer","species":"Podperson"},"5":{"name":"Pete Rattz","ckey":"mrvonstone","location":"Space","health":-29.9667,"job":"Bartender","species":"Human"},"6":{"name":"Rachel Zadovsky","ckey":"revlarss13","location":"Morgue","health":-122,"job":"Janitor","species":"Human"},"7":{"name":"Riley Garatt","ckey":"cthulhuonice","location":"Starboard Primary Hallway","health":90,"job":"Assistant","species":"Human"},"8":{"name":"Unknown","ckey":"cscottburgess","location":"Lavaland Wastes","health":-477.333,"job":"Shaft Miner","species":"Human"}},"silicons":[],"others":[],"npcs":{"Unknown":7,"blood-drunk miner":1,"bubblegum":1,"butterfly":1,"Cleanbot":2,"Inactive Camera Eye":1,"crab":3,"dwarf legion":2,"creature":1,"Floorbot":1,"goldgrub":7,"goliath":41,"grey baby slime (123)":8,"ghost":1,"hierophant":1,"hivebot":86,"Ian":1,"Legion":1,"legion":18,"Lizard":2,"monkey":13,"mouse":3,"MULEbot":2,"necropolis tendril":2,"Mysterious Medibot":1,"Officer Beep O'sky":2,"Officer Pingsky":1,"Paperwork":1,"parrot":1,"goat":1,"Pirate":1,"Pirate Gunner":1,"Poly":1,"queen bee":2,"Inactive AI Eye":1,"Runtime":1,"space carp":12,"Space Pirate":2,"Space Pirate Gunner":2,"strong hivebot":19,"Syndicate Operative":4,"Syndicate Stormtrooper":2,"Syndicate Commando":5,"Tom":1,"watcher":20}},"ghosts":{"name":"Ryan Stalh","ckey":"superturtle41"},"additional data":{"station integrity":88.6}}
