{"escapees":{"humans":{"1":{"name":"Manley Brandenburg (as Captain)","ckey":"maroondog","location":"Emergency Shuttle","health":83.9395,"job":"Station Engineer","species":"Human"},"2":{"name":"Catitao","ckey":"catmanpop","location":"Emergency Shuttle","health":69,"job":"Scientist","species":"Human"},"3":{"name":"Gabrielle Reighner","ckey":"ploogductor","location":"Emergency Shuttle","health":95,"job":"Cook","species":"Human"},"4":{"name":"Guy Fieri","ckey":"unoriginalexe","location":"Emergency Shuttle","health":80,"job":"Botanist","species":"Human"},"5":{"name":"Jetra Norlan","ckey":"azlanonpc","location":"Emergency Shuttle","health":100,"job":"Shaft Miner","species":"Human"},"6":{"name":"Landry","ckey":"landrydragon","location":"Emergency Shuttle","health":99,"job":"Head of Personnel","species":"Angel"},"7":{"name":"Lukas Wolfe","ckey":"joca2511","location":"Emergency Shuttle","health":95,"job":"Roboticist","species":"Human"},"8":{"name":"Patch-The-Hull","ckey":"swindel","location":"Emergency Shuttle","health":85,"job":"Atmospheric Technician","species":"Lizardperson"},"9":{"name":"Tah-Kepanuu","ckey":"twotar","location":"Emergency Shuttle","health":100,"job":"Scientist","species":"Luminescent"},"10":{"name":"Tends-The-Floor","ckey":"lerskull","location":"Emergency Shuttle","health":100,"job":"Janitor","species":"Lizardperson"},"11":{"name":"Ur Mom Lol","ckey":"cthulhuonice","location":"Emergency Shuttle","health":83,"job":"wizard","species":"Human"}},"silicons":[],"others":{"1":{"name":"Brief Derelict Shark","ckey":"chemicalpills5379","location":"Emergency Shuttle","health":69,"typepath":"/mob/living/simple_animal/hostile/carp/megacarp"}},"npcs":{"Cayenne":1,"Medibot":3,"Keeki":1,"kitten":21,"space cat":1,"gutlunch":1,"rabbit":1}},"abandoned":{"humans":{"1":{"name":"Argema","ckey":"arsemunster","location":"Medbay","health":82,"job":"Curator","species":"Mothmen"},"2":{"name":"Checkers","ckey":"verynisepersin","location":"Medbay","health":100,"job":"Clown","species":"Human"},"3":{"name":"Dayton Holdeman","ckey":"harukaze","location":"Fore Primary Hallway","health":100,"job":"Assistant","species":"Human"},"4":{"name":"Henry Fletcher","ckey":"spokity","location":"Atmospherics","health":-205,"job":"Atmospheric Technician","species":"Human"},"5":{"name":"Koi Alen","ckey":"coy1010allen","location":"Escape Shuttle Hallway","health":95.8,"job":"Station Engineer","species":"Human"},"6":{"name":"Lucas Osin","ckey":"ehpizza","location":"Medbay","health":100,"job":"Janitor","species":"Human"},"7":{"name":"Red Axolotl","ckey":"redaxolotl","location":"Morgue","health":-100,"job":"Roboticist","species":"Lizardperson"},"8":{"name":"Teeba-Malicus","ckey":"runrunaway","location":"Port Bow Maintenance","health":75.9,"job":"Shaft Miner","species":"Lizardperson"},"9":{"name":"Tristan Quilt","ckey":"privatetristan","location":"Starboard Bow Primary Hallway","health":-175.333,"job":"Bartender","species":"Human"},"10":{"name":"Unknown","ckey":"spaceerangerr","location":"Medbay","health":-100,"job":"Assistant","species":"Human"}},"silicons":[],"others":{"1":{"name":"Emperor penguin","ckey":"chemicalpills5379","location":"Research and Development","health":0,"typepath":"/mob/living/simple_animal/pet/penguin/emperor"},"2":{"name":"Emperor penguin","ckey":"chemicalpills5379","location":"Starboard Primary Hallway","health":0,"typepath":"/mob/living/simple_animal/pet/penguin/emperor"},"3":{"name":"George Melons","ckey":"chemicalpills5379","location":"Starboard Primary Hallway","health":100,"typepath":"/mob/living/brain"},"4":{"name":"Matt Yevpraksiya","ckey":"raddog","location":"Robotics Lab","health":100,"typepath":"/mob/living/brain"},"5":{"name":"Tun-Pad","ckey":"cthulhuonice","location":"Medbay","health":100,"typepath":"/mob/living/brain"},"6":{"name":"voidy","ckey":"raddog","location":"Research Division","health":0,"typepath":"/mob/living/simple_animal/pet/dog/corgi/puppy/void"}},"npcs":{"Medibot":1,"grey baby slime (123)":24,"Unknown":54,"Mega Space Carp":3,"Angry Stick Dog":8,"Angry Stick Man":20,"ash drake":1,"Batsy":2,"blood-drunk miner":1,"bubblegum":1,"butterfly":2,"Inactive Camera Eye":1,"chick":2,"chicken":4,"Cleanbot":1,"colossus":1,"combat bear":1,"corgi puppy":2,"corgi":1,"cow":3,"crab":1,"crate":2,"creature":12,"dwarf legion":1,"Emperor penguin":1,"eyeball":2,"fight pit bear":1,"fox":2,"ghost":2,"goldgrub":10,"goliath":30,"gondola":8,"gubbuck":1,"gutlunch":1,"hierophant":1,"hivebot":87,"Hudson":1,"Keeki":2,"kitten":242,"Legion":1,"legion":31,"Ian":1,"Lizard":3,"magmawing watcher":1,"mi-go":1,"Mjor the Creative":1,"monkey":18,"Nanotrasen Private Security Officer":12,"necropolis tendril":9,"Mysterious Medibot":1,"Officer Beep O'sky":3,"parrot":1,"pug":1,"queen bee":2,"rabbit":5,"reanimated skeleton":2,"sloth":1,"snake":4,"space bear":1,"space carp":7,"space cat":1,"space polar bear":2,"strong hivebot":19,"Swarmer":30,"swarmer beacon":1,"Syndicate Commando":2,"Syndicate Operative":16,"The Faithless":1,"viscerator":1,"void puppy":2,"watcher":26,"wumborian fugu":1}},"ghosts":{"name":"voidy","ckey":"raddog"},"additional data":{"station integrity":99}}
