{"escapees":{"humans":{"1":{"name":"Astra Void","ckey":"0omega","location":"Emergency Shuttle","health":100,"job":"Botanist","species":"Mothmen"},"2":{"name":"Jerry Robinson","ckey":"monkeyman901","location":"Escape Pod One","health":80,"job":"Assistant","species":"Human"},"3":{"name":"Landry","ckey":"landrydragon","location":"Emergency Shuttle","health":100,"job":"Chaplain","species":"Human"}},"silicons":[],"others":[],"npcs":{"Cayenne":1,"chicken":1,"cow":1,"Medibot":4}},"abandoned":{"humans":{"1":{"name":"Adalbert Heinrich","ckey":"billbobem","location":"Engineering","health":-133.475,"job":"Station Engineer","species":"Human"},"2":{"name":"Black Geezus","ckey":"pudgems","location":"Starboard Maintenance","health":-148.55,"job":"Detective","species":"Human"},"3":{"name":"Cash Pearsall","ckey":"soldiergree","location":"Dormitories","health":100,"job":"Janitor","species":"Human"},"4":{"name":"Eurosio Cuneillinio","ckey":"supe22","location":"Medbay Treatment Center","health":-97.0917,"job":"Shaft Miner","species":"Mothmen"},"5":{"name":"Henry Hank","ckey":"minitarzan","location":"Starboard Quarter Solar Maintenance","health":-51.9083,"job":"Research Director","species":"Plasmaman"},"6":{"name":"Jetra Norlan","ckey":"azlanonpc","location":"Aft Maintenance","health":-159.5,"job":"Shaft Miner","species":"Human"},"7":{"name":"John Guilliman","ckey":"lorenzoheinz","location":"Port Maintenance","health":100,"job":"Assistant","species":"Human"},"8":{"name":"Unknown","ckey":"swindel","location":"Fore Maintenance","health":-247.425,"job":"Captain","species":"Lizardperson"},"9":{"name":"Unknown","ckey":"jaxonmaxx","location":"Fore Maintenance","health":-2.99166,"job":"Warden","species":"Human"}},"silicons":{"1":{"name":"Carl","ckey":"buckyboy","location":"AI Chamber","health":100,"module":"pAI","module":"pAI"}},"others":{"1":{"name":"Runtime","ckey":"swindel","location":"Chief Medical Officer's Office","health":20,"name":"Runtime","typepath":"/mob/living/simple_animal/pet/cat/Runtime"}},"npcs":{"Angry Stick Dog":8,"Angry Stick Man":20,"Unknown":4,"basilisk":1,"bee":24,"blood-drunk miner":1,"butterfly":1,"Cleanbot":3,"Inactive AI Eye":1,"cockroach":1,"crab":1,"dwarf legion":3,"Medibot":2,"ghost":3,"creature":1,"Floorbot":1,"goldgrub":4,"goliath":48,"grey baby slime (123)":2,"hierophant":1,"Ian":1,"Pun Pun":1,"Legion":1,"legion":26,"Lizard":2,"Mjor the Creative":1,"monkey":11,"mouse":4,"MULEbot":2,"necropolis tendril":7,"Mysterious Medibot":1,"Officer Beep O'sky":2,"Officer Pingsky":1,"Paperwork":1,"goat":1,"Poly":1,"queen bee":2,"space carp":1,"Tom":1,"watcher":24}},"ghosts":{"1":{"name":"Black Geezus","ckey":"pudgems"},"2":{"name":"Eurosio Cuneillinio","ckey":"supe22"},"3":{"name":"Henry Hank","ckey":"minitarzan"},"4":{"name":"Jetra Norlan","ckey":"azlanonpc"},"5":{"name":"Meme Man","ckey":"dabaddict6969"}},"additional data":{"station integrity":99.9}}
