{"escapees":{"humans":{"1":{"name":"Erick Larson","ckey":"screeeopia","location":"Luxurious Emergency Shuttle","health":69.5,"job":"Research Director","species":"Human"},"2":{"name":"Most Likely To Be Lynched","ckey":"monkeyman901","location":"Luxurious Emergency Shuttle","health":100,"job":"Mime","species":"Human"},"3":{"name":"Samantha Warren","ckey":"jane123","location":"Luxurious Emergency Shuttle","health":100,"job":"Medical Doctor","species":"Human"},"4":{"name":"Teagan Thomas","ckey":"gimmesumsuccpls","location":"Syndicate Control Room","health":100,"job":"Unassigned","species":"Human"},"5":{"name":"Turns-theTides","ckey":"asciisquid","location":"Luxurious Emergency Shuttle","health":-124,"job":"Botanist","species":"Lizardperson"}},"silicons":[],"others":[],"npcs":{"Cayenne":1,"Medibot":2}},"abandoned":{"humans":{"1":{"name":"Aoxomoxoa Garcia","ckey":"teeminghail","location":"Engineering Foyer","health":100,"job":"Chief Engineer","species":"Human"},"2":{"name":"Ben Famen","ckey":"mk2999","location":"Security Office","health":-133.067,"job":"Head of Security","species":"Human"},"3":{"name":"Caiden Singh","ckey":"cthulhuonice","location":"Central Primary Hallway","health":60.45,"job":"Detective","species":"Human"},"4":{"name":"Casimir Leslie","ckey":"simplyviz","location":"Morgue","health":-105.667,"job":"Cook","species":"Human"},"5":{"name":"Charles H. Swanson","ckey":"darkvaderv2","location":"Arrival Shuttle Hallway","health":98.5,"job":"Chaplain","species":"Human"},"6":{"name":"Evelina Shupe","ckey":"aira23445","location":"Lavaland Wastes","health":-531.777,"job":"Beach Bum","species":"Human"},"7":{"name":"Ezekiel Heckendora","ckey":"davedtr","location":"Fore Maintenance","health":-133.333,"job":"Janitor","species":"Human"},"8":{"name":"Gregory Wright","ckey":"shawntates","location":"AI Upload Chamber","health":-100.333,"job":"Security Officer","species":"Human"},"9":{"name":"Jamie Gray","ckey":"bluetheking","location":"Cargo Office","health":-100,"job":"Cargo Technician","species":"Human"},"10":{"name":"Kadashi Sky","ckey":"lsmp","location":"Captain's Office","health":100,"job":"Assistant","species":"Human"},"11":{"name":"Kane Nash","ckey":"jubanistan","location":"Library","health":-453.322,"job":"Curator","species":"???"},"12":{"name":"Landry","ckey":"landrydragon","location":"Genetics Lab","health":-100.167,"job":"Shaft Miner","species":"Human"},"13":{"name":"Lane Fields","ckey":"oasai","location":"Space","health":-541.306,"job":"Shaft Miner","species":"Human"},"14":{"name":"Maxwell Ackerley","ckey":"joca2511","location":"Lavaland Wastes","health":-44.3367,"job":"Shaft Miner","species":"Human"},"15":{"name":"Miriam Marshall","ckey":"shawntates","location":"Lavaland Wastes","health":98,"job":"Space Bartender","species":"Human"},"16":{"name":"Misaki Fujioka","ckey":"voxskynned","location":"Genetics Lab","health":-197.167,"job":"Medical Doctor","species":"Human"},"17":{"name":"Mosquito","ckey":"wolxy","location":"Central Primary Hallway","health":24,"job":"Cargo Technician","species":"Flyperson"},"18":{"name":"Niggerpenis","ckey":"marmstoferboy","location":"Chapel Office","health":-110.667,"job":"Assistant","species":"Lizardperson"},"19":{"name":"Peter Petrograd","ckey":"datmanisdumb","location":"EVA Storage","health":-100.667,"job":"Bartender","species":"Human"},"20":{"name":"Samuel Silverstein","ckey":"dnexus","location":"Library","health":100,"job":"Roboticist","species":"Human"},"21":{"name":"Stanly Law","ckey":"xahrov","location":"Arrival Shuttle Hallway","health":90,"job":"Station Engineer","species":"Human"},"22":{"name":"Suzan Camp","ckey":"tyranor","location":"Dormitories","health":81,"job":"Station Engineer","species":"Human"},"23":{"name":"Unknown","ckey":"aira23445","location":"Kitchen","health":-185.667,"job":"Captain","species":"Human"},"24":{"name":"Unknown","ckey":"aira23445","location":"Lavaland Wastes","health":-583.82,"job":"Beach Bum","species":"Human"},"25":{"name":"Ziahri Suraheok","ckey":"robbierotten","location":"Port Quarter Maintenance","health":74.5,"job":"Atmospheric Technician","species":"Lizardperson"}},"silicons":{"1":{"name":"Fagor","ckey":"babahuhu","location":"AI Chamber","health":-127,"module":"pAI","module":"pAI"}},"others":{"1":{"name":"C.L.E.A.N.","ckey":"aira23445","location":"Robotics Lab","health":183,"typepath":"/mob/living/simple_animal/bot/cleanbot"},"2":{"name":"Grendel Stone","ckey":"braincrab","location":"Prison Wing","health":100,"typepath":"/mob/living/brain"},"3":{"name":"Kayla Moore","ckey":"luigiboiby","location":"Space","health":100,"typepath":"/mob/living/brain"}},"npcs":{"Unknown":16,"alien drone":5,"alien hunter":4,"alien empress":1,"alien sentinel":2,"ancient goliath":1,"ash drake":2,"blood-drunk miner":1,"Ian":1,"bubblegum":1,"butterfly":8,"Inactive Camera Eye":1,"Cat Surgeon":1,"crab":3,"creature":10,"Inactive AI Eye":1,"Floorbot":1,"ghost":2,"giant spider":3,"goldgrub":6,"goliath":31,"gondola":8,"grey baby slime (123)":4,"hierophant":1,"Mega Space Carp":2,"Legion":1,"legion":37,"Lizard":2,"monkey":13,"mouse":4,"necropolis tendril":11,"Mysterious Medibot":1,"Officer Beep O'sky":2,"Officer Pingsky":1,"Paperwork":1,"goat":1,"Poly":1,"queen bee":2,"Runtime":1,"space carp":34,"space cat":1,"watcher":26}},"ghosts":{"name":"MAGMA5","ckey":"halfmaster"},"additional data":{"station integrity":99.2}}
