{"escapees":{"humans":{"1":{"name":"Ben Famen","ckey":"mk2999","location":"Emergency Shuttle","health":40.5,"job":"Warden","species":"Human"},"2":{"name":"Darell Shafer","ckey":"oscswe","location":"Emergency Shuttle","health":46,"job":"Head of Personnel","species":"Human"},"3":{"name":"Gunner Lauffer","ckey":"screeeopia","location":"Emergency Shuttle","health":10.1,"job":"Shaft Miner","species":"Human"},"4":{"name":"Nicolas Singh","ckey":"cscottburgess","location":"Emergency Shuttle","health":63.1,"job":"Bartender","species":"Human"},"5":{"name":"Samantha Warren","ckey":"jane123","location":"Emergency Shuttle","health":-111.75,"job":"Security Officer","species":"Human"}},"silicons":[],"others":{"1":{"name":"Alien Emperor","ckey":"gimmesumsuccpls","location":"Emergency Shuttle","health":365,"typepath":"/mob/living/carbon/alien/humanoid/royal/queen"},"2":{"name":"alien praetorian","ckey":"mintyboi32","location":"Emergency Shuttle","health":-97.5,"typepath":"/mob/living/carbon/alien/humanoid/royal/praetorian"}},"npcs":{"Cayenne":1,"Medibot":2}},"abandoned":{"humans":{"1":{"name":"Brando Callrison","ckey":"sithis12","location":"Fore Primary Hallway","health":100,"job":"Roboticist","species":"Human"},"2":{"name":"Cindy Kate","ckey":"tonedmcstone","location":"Escape Shuttle Hallway","health":90,"job":"Medical Doctor","species":"Human"},"3":{"name":"Jerry Robinson","ckey":"monkeyman901","location":"Brig","health":89,"job":"Chemist","species":"Human"},"4":{"name":"Popeye Spinachson","ckey":"froglegsofkekistan","location":"Labor Shuttle Dock","health":-544.503,"job":"Research Director","species":"Human"},"5":{"name":"Spike Armstrong","ckey":"metalgeartoaster","location":"Starboard Primary Hallway","health":100,"job":"Assistant","species":"Human"},"6":{"name":"Unknown","ckey":"duathadruid","location":"Morgue","health":-100,"job":"Shaft Miner","species":"Human"}},"silicons":[],"others":{"1":{"name":"Barry Lotionion","ckey":"lotionabuse","location":"Space","health":100,"typepath":"/mob/living/brain"}},"npcs":{"Pun Pun":1,"Unknown":11,"alien drone":5,"alien hunter":4,"alien empress":1,"alien sentinel":2,"Angry Stick Dog":8,"Angry Stick Man":20,"ash drake":2,"basilisk":1,"bee":24,"bubblegum":1,"butterfly":8,"Cleanbot":2,"colossus":1,"crab":1,"creature":10,"Floorbot":1,"goldgrub":7,"goliath":35,"gondola":8,"grey baby slime (123)":2,"hierophant":1,"hivebot":86,"Legion":1,"legion":32,"Ian":1,"Medibot":1,"Mjor the Creative":1,"monkey":16,"mouse":5,"MULEbot":2,"necropolis tendril":11,"Mysterious Medibot":1,"Officer Beep O'sky":2,"Officer Pingsky":1,"Paperwork":1,"parrot":1,"goat":1,"Pirate":1,"Pirate Gunner":1,"Poly":1,"Runtime":1,"space carp":13,"Space Pirate":2,"Space Pirate Gunner":2,"strong hivebot":19,"Syndicate Stormtrooper":2,"Syndicate Operative":3,"Syndicate Commando":5,"Tom":1,"Lizard":1,"watcher":36}},"ghosts":{"name":"Samantha Warren","ckey":"jane123"},"additional data":{"station integrity":99.8}}
