{"escapees":{"humans":{"1":{"name":"Baylee Finlay","ckey":"barabbam","location":"Emergency Shuttle","health":71.4,"job":"Assistant","species":"Human"},"2":{"name":"Breaks-The-Bounds","ckey":"asciisquid","location":"Emergency Shuttle","health":69,"job":"Scientist","species":"Slimeperson"},"3":{"name":"Casimir Cressman","ckey":"bigpenorboi","location":"Emergency Shuttle","health":-174.867,"job":"Botanist","species":"Human"},"4":{"name":"Jeffery Jefferson (as Captain)","ckey":"jefferyjefferson","location":"Emergency Shuttle","health":26.89,"job":"Assistant","species":"Human"},"5":{"name":"Jetra Norlan","ckey":"azlanonpc","location":"Emergency Shuttle","health":-21.45,"job":"Research Director","species":"Human"},"6":{"name":"Lukas Wolfe","ckey":"joca2511","location":"Emergency Shuttle","health":26.2,"job":"Scientist","species":"Luminescent"},"7":{"name":"NIGGERS","ckey":"datmanisdumb","location":"Emergency Shuttle","health":92.5,"job":"Cook","species":"Human"},"8":{"name":"Oswald Smalls","ckey":"seamelonus","location":"Emergency Shuttle","health":58,"job":"Station Engineer","species":"Lizardperson"},"9":{"name":"Raul Tejada","ckey":"mannardo","location":"Emergency Shuttle","health":-31.6667,"job":"Chaplain","species":"Human"},"10":{"name":"Ryker Shaw","ckey":"twotar","location":"Emergency Shuttle","health":85.5333,"job":"Geneticist","species":"Human"},"11":{"name":"Guy Fieri","ckey":"unoriginalexe","location":"Emergency Shuttle","health":-13.2667,"job":"Chief Medical Officer","species":"Human"}},"silicons":[],"others":[],"npcs":{"Cayenne":1,"fight pit bear":1,"Medibot":2}},"abandoned":{"humans":{"1":{"name":"Ark Shaffer","ckey":"runian","location":"Dormitories","health":96,"job":"Janitor","species":"Human"},"2":{"name":"Bands-In-My-Pockets","ckey":"emperorryuga","location":"Mining Station EVA","health":100,"job":"Shaft Miner","species":"Human"},"3":{"name":"Henry Fletcher","ckey":"spokity","location":"Bar","health":-66,"job":"Cargo Technician","species":"Human"},"4":{"name":"Jess Jenkers","ckey":"jesslynbrooke","location":"Escape Shuttle Hallway","health":-504.052,"job":"Chemist","species":"Human"},"5":{"name":"Unknown","ckey":"pointynips","location":"Morgue","health":-441.143,"job":"Curator","species":"Human"},"6":{"name":"Rusty Iron","ckey":"mapples","location":"Lavaland Wastes","health":-488.187,"job":"Shaft Miner","species":"Human"},"7":{"name":"Scootaloo","ckey":"jizzbot3000","location":"Brig","health":86.5,"job":"Clown","species":"Human"},"8":{"name":"Unknown","ckey":"lerskull","location":"Escape Shuttle Hallway","health":62.07,"job":"Station Engineer","species":"Lizardperson"},"9":{"name":"Unknown","ckey":"oshee","location":"Genetics Lab","health":-166.667,"job":"Head of Personnel","species":"Human"},"10":{"name":"Unknown","ckey":"ilovess13","location":"EVA Storage","health":-508.39,"job":"Warden","species":"Human"},"11":{"name":"Wack Grandpap","ckey":"arrfur","location":"Genetics Lab","health":-103,"job":"Scientist","species":"Human"},"12":{"name":"Wall Runner","ckey":"raddog","location":"Brig","health":59.67,"job":"Mime","species":"Human"},"13":{"name":"Warrior Three Taps","ckey":"disrespectisrespect","location":"Bridge","health":90,"job":"Virologist","species":"Human"},"14":{"name":"Yukikage Sora","ckey":"goldentouch","location":"Medbay Central","health":2,"job":"Shaft Miner","species":"Human"}},"silicons":[],"others":{"1":{"name":"Adolf Weissman","ckey":"sevenraiden","location":"Brig","health":100,"typepath":"/mob/living/brain"},"2":{"name":"Cadence Bullard","ckey":"apocalypticprime","location":"Genetics Lab","health":100,"typepath":"/mob/living/brain"},"3":{"name":"Raul Otis","ckey":"spodermen11","location":"Arrival Shuttle Hallway","health":100,"typepath":"/mob/living/brain"},"4":{"name":"Warrior One Tap","ckey":"respectisdisrespect","location":"Medbay Central","health":100,"typepath":"/mob/living/brain"},"5":{"name":"Sloppy Joe","ckey":"drunkenpeasant","location":"Labor Shuttle Dock","health":100,"typepath":"/mob/living/brain"},"6":{"name":"Lee Crow","ckey":"dsgkl","location":"Brig","health":100,"typepath":"/mob/living/brain"}},"npcs":{"Unknown":33,"ash drake":1,"bubblegum":1,"Cleanbot":2,"Inactive Camera Eye":2,"dwarf legion":2,"creature":10,"fight pit bear":1,"Floorbot":1,"ghost":3,"grey baby slime (123)":23,"goldgrub":4,"goliath":24,"gondola":8,"brain":1,"hierophant":1,"hivebot":86,"Ian":1,"Legion":1,"legion":19,"monkey":19,"mouse":1,"MULEbot":2,"necropolis tendril":2,"Mysterious Medibot":1,"Officer Beep O'sky":2,"Officer Pingsky":1,"Paperwork":1,"Poly":1,"Pun Pun":1,"Runtime":1,"space carp":7,"strong hivebot":19,"Syndicate Operative":1,"Tom":1,"undead eskimo":2,"Lizard":1,"watcher":18}},"ghosts":{"name":"Casimir Cressman","ckey":"bigpenorboi"},"additional data":{"station integrity":98.2}}
