{"escapees":{"humans":{"1":{"name":"Catitao","ckey":"catmanpop","location":"Emergency Shuttle","health":88.67,"job":"Medical Doctor","species":"Human"},"2":{"name":"Gael Mcloskey","ckey":"verillius","location":"Emergency Shuttle","health":99,"job":"Shaft Miner","species":"Human"},"3":{"name":"Jeffery Jefferson","ckey":"jefferyjefferson","location":"Emergency Shuttle","health":69.5,"job":"Head of Personnel","species":"Human"},"4":{"name":"Jhonson Lutherfield","ckey":"iagotodesco","location":"Emergency Shuttle","health":100,"job":"Roboticist","species":"Human"},"5":{"name":"Kolton Rhinehart","ckey":"manmail","location":"Emergency Shuttle","health":100,"job":"Scientist","species":"Human"},"6":{"name":"Sandra Parker","ckey":"thoreaufare","location":"Emergency Shuttle","health":35,"job":"Shaft Miner","species":"Human"},"7":{"name":"Jack Gray","ckey":"re1taz","location":"Emergency Shuttle","health":99,"job":"Lawyer","species":"Human"},"8":{"name":"Bronte Lowe","ckey":"re1taz","location":"CentCom Recovery Ship","health":100,"job":"Unassigned","species":"Human"},"9":{"name":"Mekhi Knapp","ckey":"re12","location":"CentCom Recovery Ship","health":100,"job":"Unassigned","species":"Human"},"10":{"name":"Audrey Paynter","ckey":"ddanik","location":"CentCom Recovery Ship","health":100,"job":"Unassigned","species":"Human"}},"silicons":[],"others":[],"npcs":{"Cayenne":1,"ghost":1,"Ian":1,"Medibot":2}},"abandoned":{"humans":{"1":{"name":"Adamantine Dacite","ckey":"ddanik","location":"Mining Station Port Wing","health":-424.742,"job":"Free Golem","species":"Adamantine Golem"},"2":{"name":"Benny Tequilla","ckey":"mrcheese1","location":"Hydroponics","health":100,"job":"Botanist","species":"???"},"3":{"name":"Gragnir Grolob","ckey":"haggisshuu","location":"Space","health":-246.673,"job":"Janitor","species":"Human"},"4":{"name":"Hailee Blessig","ckey":"re1taz","location":"Morgue","health":-101.883,"job":"Unassigned","species":"Human"},"5":{"name":"Hartley Riggle","ckey":"tythesmonk","location":"Starboard Primary Hallway","health":100,"job":"Security Officer","species":"Human"},"6":{"name":"Helps-The-Station","ckey":"greentea98","location":"Kitchen","health":100,"job":"Cook","species":"Lizardperson"},"7":{"name":"Isaac Wile","ckey":"disguiser","location":"Cargo Office","health":99,"job":"Security Officer","species":"Human"},"8":{"name":"Kailey Elliott","ckey":"whoneedspacee","location":"Lavaland Wastes","health":-601.99,"job":"Shaft Miner","species":"Human"},"9":{"name":"Luna White","ckey":"spoder13","location":"Charlie Station Main Corridor","health":100,"job":"Ancient Crew","species":"Human"},"10":{"name":"Making The Music","ckey":"blazikenowen","location":"Bar","health":-112.63,"job":"Chaplain","species":"Lizardperson"},"11":{"name":"Patch-The-Hull","ckey":"swindel","location":"Chief Engineer's Office","health":100,"job":"Chief Engineer","species":"Lizardperson"},"12":{"name":"Sandra Parker","ckey":"spoder13","location":"Morgue","health":-141,"job":"Scientist","species":"Human"},"13":{"name":"Tyron Reade","ckey":"ilovess13","location":"Brig Control","health":66.5,"job":"Warden","species":"Human"}},"silicons":[],"others":[],"npcs":{"Angry Stick Dog":8,"Angry Stick Man":20,"ash drake":2,"Unknown":36,"basilisk":1,"bee":24,"bubblegum":1,"butterfly":8,"Cleanbot":2,"Cat Surgeon":1,"ghost":1,"colossus":1,"crab":1,"creature":19,"dwarf legion":1,"Floorbot":1,"goldgrub":8,"goliath":27,"gondola":8,"grey baby slime (123)":2,"hierophant":1,"hivebot":86,"Legion":1,"legion":31,"Mjor the Creative":1,"monkey":11,"mouse":6,"MULEbot":2,"necropolis tendril":9,"Mysterious Medibot":1,"Officer Beep O'sky":2,"Officer Pingsky":1,"Paperwork":1,"parrot":1,"goat":1,"Pirate":1,"Pirate Gunner":1,"Poly":1,"Runtime":1,"space carp":13,"space cat":1,"Space Pirate":2,"Space Pirate Gunner":2,"strong hivebot":19,"Syndicate Commando":6,"Syndicate Operative":23,"Syndicate Stormtrooper":2,"The Faithless":64,"Tom":1,"undead eskimo":2,"Lizard":1,"watcher":29}},"ghosts":{"name":"nanotrasen minebot","ckey":"buckyboy"},"additional data":{"station integrity":99.9}}
