{"escapees":{"humans":[],"silicons":[],"others":[],"npcs":[]},"abandoned":{"humans":{"1":{"name":"Matt Yevpraksiya","ckey":"raddog","location":"Bar","health":-100,"job":"Quartermaster","species":"Human"},"2":{"name":"Carson Ryals","ckey":"busnesmun","location":"Arrival Shuttle Hallway","health":85.05,"job":"Head of Personnel","species":"Human"},"3":{"name":"Bab","ckey":"shammakh2","location":"Starboard Maintenance","health":-67.1699,"job":"Captain","species":"Human"},"4":{"name":"Mike Wadibidowski","ckey":"re1taz","location":"Captain's Office","health":85,"job":"Chaplain","species":"Human"},"5":{"name":"Wack Grandpap","ckey":"arrfur","location":"Central Primary Hallway","health":85,"job":"Chief Engineer","species":"Human"}},"silicons":[],"others":[],"npcs":{"ancient goliath":1,"Angry Stick Dog":8,"Angry Stick Man":20,"ash drake":1,"Penguin chick":1,"blood-drunk miner":1,"bubblegum":1,"butterfly":1,"Cleanbot":2,"Unknown":8,"Cat Surgeon":1,"Cayenne":1,"dwarf legion":2,"creature":1,"Floorbot":1,"ghost":3,"goldgrub":3,"goliath":43,"gondola":8,"grey baby slime (123)":2,"hierophant":1,"hivebot":86,"Ian":1,"Legion":1,"legion":23,"Medibot":2,"Mjor the Creative":1,"monkey":11,"MULEbot":2,"necropolis tendril":6,"Mysterious Medibot":1,"Officer Beep O'sky":2,"Officer Pingsky":1,"Paperwork":1,"goat":1,"Poly":1,"rabbit":64,"Runtime":1,"space carp":7,"space cat":1,"Spaceman":3,"strong hivebot":19,"Syndicate Operative":1,"Tom":1,"Lizard":1,"watcher":24,"mouse":6}},"ghosts":{"name":"Matt Yevpraksiya","ckey":"raddog"},"additional data":{"station integrity":99.8}}
