{"escapees":{"humans":{"1":{"name":"Azrael Watts","ckey":"azraelknightquest","location":"Emergency Shuttle","health":-114.5,"job":"Head of Security","species":"Human"},"2":{"name":"Christian Altmann","ckey":"bilary","location":"Emergency Shuttle","health":-108.875,"job":"Quartermaster","species":"Human"},"3":{"name":"Eva","ckey":"mayhem88","location":"CentCom Recovery Ship","health":-101.825,"job":"Warden","species":"Lizardperson"},"4":{"name":"Jetra Norlan","ckey":"azlanonpc","location":"CentCom Recovery Ship","health":99.5,"job":"Shaft Miner","species":"Human"},"5":{"name":"Mr Fluffles","ckey":"juicychicken","location":"CentCom Recovery Ship","health":-129.442,"job":"Roboticist","species":"Mothmen"},"6":{"name":"Simon Fenix","ckey":"smarrazzo","location":"Emergency Shuttle","health":-162.988,"job":"Research Director","species":"Human"},"7":{"name":"Tom Anderson","ckey":"supersunfish","location":"CentCom Recovery Ship","health":-90.025,"job":"Assistant","species":"Human"},"8":{"name":"Tyron Jamal","ckey":"davidththird","location":"CentCom Recovery Ship","health":-90.8667,"job":"Assistant","species":"Human"}},"silicons":{"1":{"name":"S.A.S shell 213 - Security","ckey":"buckyboy","location":"CentCom Recovery Ship","health":17.5,"module":"Security"}},"others":{"1":{"name":"Phantom of silent ruin","ckey":"neapher","location":"CentCom Recovery Ship","health":1e+31,"name":"Phantom of silent ruin","typepath":"/mob/living/simple_animal/revenant"}},"npcs":{"Cayenne":1,"chicken":1,"cow":1,"Medibot":4,"Cyborg":2}},"abandoned":{"humans":{"1":{"name":"Amaya Adams","ckey":"stalinho","location":"Charlie Station Main Corridor","health":-100.233,"job":"Ancient Crew","species":"Human"},"2":{"name":"Baldric Mcmullen","ckey":"dantas909090","location":"Charlie Station Main Corridor","health":-100.167,"job":"Ancient Crew","species":"Human"},"3":{"name":"Camden Rohtin","ckey":"blazikenowen","location":"Syndicate Lavaland Primary Hallway","health":-307.65,"job":"Lavaland Syndicate","species":"Human"},"4":{"name":"Christa Schofield","ckey":"tanper","location":"Law Office","health":8,"job":"Lawyer","species":"Human"},"5":{"name":"Gabriella Clark","ckey":"esculate","location":"Arrival Shuttle Hallway","health":100,"job":"Station Engineer","species":"Xenobiological Jelly Entity"},"6":{"name":"Gordon Green","ckey":"viaod4","location":"Morgue","health":-210.667,"job":"Station Engineer","species":"Human"},"7":{"name":"Kaito 'Dagger' Haunting","ckey":"catmanpop","location":"Warehouse","health":64.375,"job":"Scientist","species":"Human"},"8":{"name":"Medium Brother","ckey":"bobcat49","location":"Aft Maintenance","health":-72,"job":"Virologist","species":"Human"},"9":{"name":"Nydia Bode","ckey":"markgman","location":"Engineering","health":-100.147,"job":"Medical Doctor","species":"Human"},"10":{"name":"Tami Paxton","ckey":"neapher","location":"Genetics Lab","health":-121.15,"job":"Security Officer","species":"Human"},"11":{"name":"Tamsin Mingle","ckey":"markgman","location":"Charlie Station Main Corridor","health":-100.583,"job":"Ancient Crew","species":"Human"},"12":{"name":"Tristen Hanford","ckey":"blazikenowen","location":"Syndicate Lavaland Primary Hallway","health":-652.6,"job":"Lavaland Syndicate","species":"Human"}},"silicons":[],"others":{"1":{"name":"Camden Rohtin","ckey":"blazikenowen","location":"Syndicate Lavaland Medbay","health":100,"name":"Camden Rohtin","typepath":"/mob/living/brain"},"2":{"name":"Drake Knapp","ckey":"viaod4","location":"Syndicate Lavaland Primary Hallway","health":100,"name":"Drake Knapp","typepath":"/mob/living/brain"},"3":{"name":"Jack Gray","ckey":"re1taz","location":"Robotics Lab","health":100,"name":"Jack Gray","typepath":"/mob/living/brain"},"4":{"name":"orange baby slime (378)","ckey":"bobcat49","location":"Xenobiology Lab","health":0,"name":"orange baby slime (378)","typepath":"/mob/living/simple_animal/slime"},"5":{"name":"Pop","ckey":"blazikenowen","location":"Robotics Lab","health":100,"name":"Pop","typepath":"/mob/living/brain"}},"npcs":{"Unknown":22,"ash drake":1,"blood-drunk miner":1,"bubblegum":1,"butterfly":1,"Cleanbot":15,"Inactive Camera Eye":1,"combat bear":2,"dwarf legion":2,"ED-209 Security Robot":2,"creature":1,"Floorbot":1,"ghost":4,"goldgrub":9,"goliath":32,"gondola":8,"grey baby slime (123)":3,"hierophant":1,"hivebot":86,"Ian":1,"Pun Pun":1,"Legion":1,"legion":11,"monkey":17,"MULEbot":1,"necropolis tendril":7,"Mysterious Medibot":1,"Officer Beep O'sky":2,"Officer Pingsky":1,"Paperwork":1,"parrot":1,"goat":1,"Pirate":1,"Pirate Gunner":2,"Poly":1,"Runtime":1,"AI":1,"Inactive AI Eye":1,"Securitron":2,"space carp":12,"Space Pirate Gunner":4,"strong hivebot":19,"Syndicate Stormtrooper":2,"Syndicate Salvage Pilot":2,"Syndicate Commando":5,"Lizard":1,"watcher":27}},"ghosts":{"1":{"name":"Baldric Mcmullen","ckey":"dantas909090"},"2":{"name":"Christian Altmann","ckey":"bilary"},"3":{"name":"Drake Knapp","ckey":"viaod4"},"4":{"name":"Eva","ckey":"mayhem88"},"5":{"name":"Katherine Cowper","ckey":"mlggendalf"},"6":{"name":"Mr Fluffles","ckey":"juicychicken"},"7":{"name":"orange adult slime (917)","ckey":"bobcat49"},"8":{"name":"Simon Fenix","ckey":"smarrazzo"},"9":{"name":"Tamsin Mingle","ckey":"markgman"},"10":{"name":"Tom Anderson","ckey":"supersunfish"},"11":{"name":"Tristen Hanford","ckey":"blazikenowen"},"12":{"name":"Tyron Jamal","ckey":"davidththird"}},"additional data":{"station integrity":98.4}}
