{"escapees":{"humans":{"1":{"name":"Helps-The-Station","ckey":"greentea98","location":"Emergency Shuttle","health":99.4,"job":"Chief Engineer","species":"Lizardperson"},"2":{"name":"Jess Jenkers","ckey":"jesslynbrooke","location":"Emergency Shuttle","health":75.7,"job":"Medical Doctor","species":"Angel"},"3":{"name":"Rose White","ckey":"bobcat49","location":"Emergency Shuttle","health":100,"job":"Roboticist","species":"Human"},"4":{"name":"Woolie Nammers","ckey":"mrcheese1","location":"Emergency Shuttle","health":90,"job":"Shaft Miner","species":"Mothman"}},"silicons":[],"others":[],"npcs":{"Cleanbot":1,"Cayenne":1,"chicken":2,"Exotic Corgi":1,"cow":2,"fox":1,"Medibot":4,"kitten":6,"Unknown":1,"Proc":1,"pug":1,"Runtime":1,"brain":1}},"abandoned":{"humans":{"1":{"name":"Ariana Styles","ckey":"yiffsinhell","location":"Medbay Treatment Center","health":100,"job":"Security Officer","species":"Human"},"2":{"name":"Eli Norton","ckey":"hercbeet","location":"Snowdin Outpost - Research Area","health":-100,"job":"Unassigned","species":"Human"},"3":{"name":"Eli Norton","ckey":"hercbeet","location":"Morgue","health":-98.7,"job":"Medical Doctor","species":"Human"},"4":{"name":"Hossein Khosrow Ali Vaziri","ckey":"penginh","location":"Armory","health":96.2,"job":"Head of Personnel","species":"Human"},"5":{"name":"Jetra Norlan","ckey":"azlanonpc","location":"Mining Station Port Wing","health":76,"job":"Shaft Miner","species":"Human"},"6":{"name":"Landry","ckey":"landrydragon","location":"Dormitories","health":96.7,"job":"Detective","species":"Human"},"7":{"name":"Lara Black","ckey":"bilary","location":"Engineering","health":-100.3,"job":"Station Engineer","species":"Human"},"8":{"name":"Leonard Paynter","ckey":"blackman60","location":"Medbay Treatment Center","health":-100,"job":"Security Officer","species":"Human"},"9":{"name":"Moth Salts","ckey":"lukanoktorios","location":"Arrival Shuttle Hallway","health":-100.3,"job":"Station Engineer","species":"Mothman"},"10":{"name":"Peter Parker","ckey":"jaedo","location":"Waste Disposal","health":-102.3,"job":"Cook","species":"Human"},"11":{"name":"Rotting Carcass","ckey":"juicychicken","location":"Mining Station Port Wing","health":80,"job":"Research Director","species":"Human"},"12":{"name":"Unknown","ckey":"papaputin","location":"Lavaland Wastes","health":-496.9,"job":"Chief Medical Officer","species":"Lizardperson"}},"silicons":[],"others":[],"npcs":{"Medibot":1,"Unknown":38,"ash drake":2,"basilisk":19,"bee":24,"blank body":9,"bubblegum":1,"Inactive Camera Eye":2,"ice skeleton":19,"Cat Surgeon":1,"Cleanbot":2,"colossus":5,"corgi":1,"crab":1,"creature":15,"dwarf legion":2,"Floorbot":1,"giant ice spider":8,"goldgrub":11,"goliath":30,"hierophant":1,"hivebot":86,"kitten":4,"Legion":1,"legion":17,"mi-go":10,"monkey":11,"MULEbot":2,"nanotrasen minebot":1,"necropolis tendril":2,"netherworld link":4,"Mysterious Medibot":1,"Pun Pun":1,"Officer Beep O'sky":2,"Officer Pingsky":1,"Paperwork":1,"goat":1,"Poly":1,"shambling miner":9,"space carp":8,"space cat":1,"space polar bear":16,"Spaceman":3,"strong hivebot":19,"Syndicate Operative":1,"undead eskimo":11,"undead templar":10,"Lizard":1,"watcher":16}},"ghosts":{"1":{"name":"Amari Sandys","ckey":"swordfish342"},"2":{"name":"Leonard Paynter","ckey":"blackman60"},"3":{"name":"Peter Parker","ckey":"jaedo"},"4":{"name":"Sucks-The-Dick","ckey":"papaputin"}},"additional data":{"station integrity":99.8}}
