{"escapees":{"humans":{"1":{"name":"Unknown","ckey":"mlggendalf","location":"Emergency Shuttle","health":62,"job":"Virologist","species":"Human"},"2":{"name":"Unknown","ckey":"moonmanmoonman","location":"Escape Pod Three","health":89,"job":"Cook","species":"Human"},"3":{"name":"Unknown","ckey":"infinitystrueend","location":"Emergency Shuttle","health":90,"job":"Curator","species":"Lizardperson"},"4":{"name":"Unknown","ckey":"greentea98","location":"Emergency Shuttle","health":100,"job":"Assistant","species":"Lizardperson"},"5":{"name":"Unknown","ckey":"swindel","location":"Escape Pod Four","health":75.3,"job":"Head of Security","species":"Human"},"6":{"name":"Unknown","ckey":"charlors","location":"Emergency Shuttle","health":93.34,"job":"Janitor","species":"Human"},"7":{"name":"Unknown","ckey":"goodieboy","location":"Emergency Shuttle","health":67.17,"job":"Chemist","species":"Human"}},"silicons":[],"others":[],"npcs":{"Cayenne":1,"Medibot":2}},"abandoned":{"humans":{"1":{"name":"Braeden Sholl","ckey":"joca2511","location":"Medbay Central","health":-529.152,"job":"Security Officer","species":"Human"},"2":{"name":"Caryl Echard","ckey":"ddanik","location":"Syndicate Lavaland Engineering","health":77.5,"job":"Lavaland Syndicate","species":"Human"},"3":{"name":"Christiana Staymates","ckey":"kag3rou","location":"Robotics Lab","health":99.5,"job":"Research Director","species":"Human"},"4":{"name":"Eveleen Johnson","ckey":"danthegrump","location":"Starboard Maintenance","health":-100,"job":"Assistant","species":"Human"},"5":{"name":"Gragnir Grolob","ckey":"haggisshuu","location":"Central Primary Hallway","health":-423.383,"job":"Bartender","species":"Human"},"6":{"name":"Gregory Wright","ckey":"shawntates","location":"Port Maintenance","health":-669.126,"job":"Security Officer","species":"Human"},"7":{"name":"Jack Gray","ckey":"re1taz","location":"Teleporter Room","health":-100,"job":"Captain","species":"Human"},"8":{"name":"Motya Zhenya (as Jack Gray)","ckey":"raddog","location":"Hotel","health":-100.084,"job":"Scientist","species":"Human"},"9":{"name":"Raul Tejada","ckey":"mannardo","location":"Space","health":-555.206,"job":"Roboticist","species":"Human"},"10":{"name":"Santiago Clark","ckey":"shawntates","location":"Syndicate Lavaland Primary Hallway","health":80.5,"job":"Lavaland Syndicate","species":"Human"},"11":{"name":"Tyrone Negrone","ckey":"capietro","location":"Port Quarter Maintenance","health":-101.833,"job":"Botanist","species":"Human"},"12":{"name":"Jonathon Eckhardstein","ckey":"pureleper","location":"Syndicate Lavaland Bar","health":97,"job":"Lavaland Syndicate","species":"Human"},"13":{"name":"Unknown","ckey":"wilsobum","location":"Brig Control","health":-166.167,"job":"Station Engineer","species":"Human"},"14":{"name":"Unknown","ckey":"bobcat49","location":"Medbay Central","health":-475.583,"job":"Shaft Miner","species":"Human"},"15":{"name":"Unknown","ckey":"moontruther","location":"Space","health":-493.913,"job":"Chaplain","species":"Human"}},"silicons":{"1":{"name":"B.O.I.","ckey":"kevinspacey2002","location":"AI Chamber","health":100,"module":"pAI","module":"pAI"}},"others":{"1":{"name":"cogscarab (355)","ckey":"vega12","location":"City of Cogs","health":50,"typepath":"/mob/living/simple_animal/drone/cogscarab/ratvar"},"2":{"name":"cogscarab (5)","ckey":"jefferyjefferson","location":"City of Cogs","health":50,"typepath":"/mob/living/simple_animal/drone/cogscarab/ratvar"},"3":{"name":"Tyron Reade","ckey":"ilovess13","location":"Starboard Maintenance","health":100,"typepath":"/mob/living/brain"}},"npcs":{"Medibot":1,"Angry Stick Dog":8,"Angry Stick Man":20,"Unknown":28,"ash drake":3,"Inactive AI Eye":1,"blood-drunk miner":1,"bubblegum":1,"Inactive Camera Eye":3,"Cleanbot":2,"colossus":4,"crab":3,"creature":1,"Floorbot":1,"goldgrub":9,"goliath":39,"gondola":8,"grey baby slime (123)":2,"hierophant":1,"Ian":1,"icewing watcher":1,"Legion":1,"legion":20,"Lizard":2,"Mjor the Creative":1,"monkey":12,"mouse":2,"MULEbot":2,"necropolis tendril":5,"Mysterious Medibot":1,"Officer Beep O'sky":2,"Officer Pingsky":1,"Paperwork":1,"goat":1,"Poly":1,"Runtime":1,"Syndicate Operative":1,"Tom":1,"ghost":1,"watcher":38}},"ghosts":{"name":"Tyrone Negrone","ckey":"capietro"},"additional data":{"station integrity":92.3}}
