{"escapees":{"humans":{"1":{"name":"Brian Ski","ckey":"beeskee","location":"Luxurious Emergency Shuttle","health":78.83,"job":"Curator","species":"Human"}},"silicons":[],"others":[],"npcs":{"Cayenne":1,"Medibot":2}},"abandoned":{"humans":[],"silicons":[],"others":[],"npcs":{"Mysterious Medibot":1,"creature":1,"Paperwork":1,"MULEbot":2,"Officer Beep O'sky":2,"Tom":1,"Ian":1,"Poly":1,"Lizard":1,"Pun Pun":1,"Cleanbot":2,"Floorbot":1,"Officer Pingsky":1,"goat":1,"monkey":11,"Runtime":1,"grey baby slime (123)":2,"Legion":1,"hierophant":1,"undead eskimo":2,"alien drone":10,"alien empress":2,"alien sentinel":4,"alien hunter":8,"blood-drunk miner":1,"butterfly":1,"Medibot":1,"goldgrub":9,"crab":1,"space carp":1,"basilisk":1,"bee":24,"Unknown":7,"Syndicate Operative":1,"legion":40,"bubblegum":1,"ash drake":5,"necropolis tendril":12,"goliath":51,"watcher":29,"colossus":2,"mouse":7}},"ghosts":[],"additional data":{"station integrity":100}}
