{"escapees":{"humans":{"1":{"name":"Gavin Kellogg","ckey":"kevinspacey2002","location":"Emergency Shuttle","health":100,"job":"Head of Security","species":"Human"},"2":{"name":"Jetra Norlan","ckey":"azlanonpc","location":"Escape Pod One","health":65,"job":"Shaft Miner","species":"Human"},"3":{"name":"Julia Luna","ckey":"qwertyquerty","location":"Emergency Shuttle","health":100,"job":"Chemist","species":"Human"},"4":{"name":"Lisa Standley","ckey":"darktplaysbr","location":"Emergency Shuttle","health":80,"job":"Chemist","species":"Human"},"5":{"name":"Ruru","ckey":"boxxybooty","location":"Emergency Shuttle","health":100,"job":"Captain","species":"Human"},"6":{"name":"Seeks-The-Truths","ckey":"asciisquid","location":"Emergency Shuttle","health":-32.3367,"job":"Shaft Miner","species":"Lizardperson"},"7":{"name":"Theodore Eliza","ckey":"kelesis","location":"Emergency Shuttle","health":100,"job":"Cargo Technician","species":"Human"},"8":{"name":"Walo Igie","ckey":"boxtastic","location":"Emergency Shuttle","health":62.35,"job":"Head of Personnel","species":"Human"}},"silicons":{"1":{"name":"Lou Igie","ckey":"luigi69420","location":"Emergency Shuttle","health":500}},"others":[],"npcs":{"Cayenne":1,"chicken":1,"cow":1,"Medibot":3,"Mysterious Medibot":1}},"abandoned":{"humans":{"1":{"name":"Alec Cooper","ckey":"coolcatisfeelinggroovy","location":"Deep Storage Recycler","health":-322.64,"job":"Chaplain","species":"Human"},"2":{"name":"Beau Richards","ckey":"buckyboy","location":"Deep Storage Recycler","health":-230,"job":"Scientist","species":"Human"},"3":{"name":"Chris Redding","ckey":"berrymann","location":"Arrival Shuttle Hallway","health":89,"job":"Bartender","species":"Human"},"4":{"name":"Elle Sanders","ckey":"mayhem88","location":"the Unexplored Location","health":100,"job":"Space Bartender","species":"Human"},"5":{"name":"Jamie Demuth","ckey":"nikolasskimze","location":"Deep Storage","health":38.5,"job":"Chief Medical Officer","species":"Human"},"6":{"name":"Lou Igie","ckey":"luigi69420","location":"Lavaland Wastes","health":-510.409,"job":"Shaft Miner","species":"Human"},"7":{"name":"Mark Ryals","ckey":"davidblanc","location":"Deep Storage Recycler","health":-338,"job":"Security Officer","species":"Human"},"8":{"name":"Taqi Al-Rafiq","ckey":"mannardo","location":"Port Quarter Maintenance","health":-100.048,"job":"Assistant","species":"Human"},"9":{"name":"Tul-Ullis","ckey":"swindel","location":"Deep Storage Power and Atmospherics Room","health":72.66,"job":"Assistant","species":"Lizardperson"},"10":{"name":"Unknown","ckey":"mayhem88","location":"Lavaland Wastes","health":-518.863,"job":"Translocated Vet","species":"Human"},"11":{"name":"Unknown","ckey":"re1taz","location":"Deep Storage","health":66.5,"job":"Assistant","species":"Human"},"12":{"name":"Unknown","ckey":"pandolphina","location":"Space","health":92.17,"job":"Hotel Staff","species":"Human"},"13":{"name":"Unknown","ckey":"jaxonmaxx","location":"Escape Shuttle Hallway","health":100,"job":"Mime","species":"Human"},"14":{"name":"Unknown","ckey":"braincrab","location":"Deep Storage Dormory","health":100,"job":"Chief Engineer","species":"Human"},"15":{"name":"Unknown","ckey":"coolcatisfeelinggroovy","location":"XCC-P5831 Kitchen Arena","health":100,"job":"Unassigned","species":"Human"},"16":{"name":"Unknown","ckey":"ceanox","location":"Genetics Lab","health":-105,"job":"Clown","species":"Human"},"17":{"name":"Unknown","ckey":"mayhem88","location":"Lavaland Wastes","health":-544.55,"job":"Beach Bum","species":"Human"}},"silicons":{"1":{"name":"Chippy","ckey":"mayhem88","location":"Deep Storage Power and Atmospherics Room","health":100,"module":"Default"},"2":{"name":"FRA.G.M.E.N.T","ckey":"swindel","location":"AI Chamber","health":100,"module":"pAI","module":"pAI"}},"others":[],"npcs":{"Medibot":3,"Unknown":16,"ash drake":2,"Penguin chick":1,"blood-drunk miner":1,"Cleanbot":7,"Cat Surgeon":1,"colossus":1,"cow":20,"crab":3,"brain":1,"creature":1,"Floorbot":1,"Inactive AI Eye":1,"goldgrub":5,"goliath":28,"gondola":8,"grey baby slime (123)":2,"hierophant":1,"corgi puppy":1,"Legion":1,"legion":5,"Lizard":2,"monkey":11,"mouse":3,"MULEbot":2,"necropolis tendril":2,"Mysterious Medibot":1,"Officer Beep O'sky":2,"Officer Pingsky":1,"Paperwork":1,"goat":1,"Poly":1,"Runtime":1,"space cat":1,"Tom":1,"watcher":11,"ghost":1}},"ghosts":{"1":{"name":"Alec Cooper","ckey":"coolcatisfeelinggroovy"},"2":{"name":"Beau Richards","ckey":"buckyboy"},"3":{"name":"Bonker","ckey":"ceanox"},"4":{"name":"strong hivebot","ckey":"disguiser"},"5":{"name":"Taqi Al-Rafiq","ckey":"mannardo"}},"additional data":{"station integrity":99.8}}
