{"escapees":{"humans":{"1":{"name":"Henry Fletcher","ckey":"spokity","location":"Emergency Shuttle","health":-188.5,"job":"Shaft Miner","species":"Human"},"2":{"name":"Marco Polo","ckey":"enukar","location":"Emergency Shuttle","health":90,"job":"Scientist","species":"Human"},"3":{"name":"Unknown","ckey":"lumirelivi","location":"Emergency Shuttle","health":-229.833,"job":"Shaft Miner","species":"Human"}},"silicons":{"1":{"name":"kill marco polo","ckey":"sufferedbobcat","location":"Emergency Shuttle","health":500}},"others":[],"npcs":{"Cayenne":1,"fight pit bear":3,"Medibot":2,"Unknown":1}},"abandoned":{"humans":{"1":{"name":"Ainsley Treeby","ckey":"swatblack","location":"Charlie Station Main Corridor","health":100,"job":"Ancient Crew","species":"Human"},"2":{"name":"Captain","ckey":"plon2","location":"Space","health":-502.076,"job":"Station Engineer","species":"Human"},"3":{"name":"Jazlyn Ahmed","ckey":"swatblack","location":"Space","health":-597.9,"job":"Ancient Crew","species":"Human"},"4":{"name":"Unknown","ckey":"sufferedbobcat","location":"Space","health":-519.616,"job":"Head of Security","species":"Human"}},"silicons":{"1":{"name":"Door Bot","ckey":"pyrotwister","location":"AI Chamber","health":-165,"module":"pAI","module":"pAI"}},"others":{"1":{"name":"Jason Valkerie","ckey":"astronautcat","location":"Arrival Shuttle Hallway","health":100,"typepath":"/mob/living/brain"}},"npcs":{"Unknown":7,"alien drone":5,"alien hunter":4,"alien empress":1,"alien sentinel":2,"Angry Stick Dog":8,"Angry Stick Man":20,"ash drake":4,"Cleanbot":2,"Inactive Camera Eye":1,"Cat Surgeon":1,"Clown":1,"creature":2,"Inactive AI Eye":1,"slaughter demon":1,"Floorbot":1,"giant spider":2,"goldgrub":9,"goliath":56,"grey baby slime (123)":8,"hierophant":1,"hivebot":86,"Ian":1,"Pun Pun":1,"Legion":1,"legion":33,"Lizard":2,"magicarp":9,"Mjor the Creative":1,"monkey":15,"mouse":4,"MULEbot":2,"necropolis tendril":23,"Mysterious Medibot":1,"Officer Beep O'sky":2,"Officer Pingsky":1,"Paperwork":1,"Poly":1,"reanimated skeleton":5,"morph":1,"Runtime":1,"Space Bat":6,"space bear":6,"space carp":7,"space cat":1,"Space Wizard":26,"strong hivebot":19,"Swarmer":30,"swarmer beacon":1,"Syndicate Operative":2,"Tom":1,"undead eskimo":2,"watcher":31}},"ghosts":{"name":"Phoenix Davis","ckey":"booshant"},"additional data":{"station integrity":99.3}}
