{"escapees":{"humans":{"1":{"name":"Landry","ckey":"landrydragon","location":"Emergency Shuttle","health":100,"job":"Chief Engineer","species":"Human"}},"silicons":[],"others":[],"npcs":{"Cayenne":1,"Medibot":2}},"abandoned":{"humans":{"1":{"name":"Kagamine Rin","ckey":"catmanpop","location":"Arrival Shuttle Hallway","health":96.33,"job":"Medical Doctor","species":"Human"},"2":{"name":"Lukas Wolfe","ckey":"joca2511","location":"Space","health":-100,"job":"Roboticist","species":"Human"},"3":{"name":"Unknown","ckey":"brhunter45","location":"Mining Station Starboard Wing","health":-508.1,"job":"Ash Walker","species":"Ash Walker"}},"silicons":[],"others":{"1":{"name":"Breaks-The-Bounds","ckey":"asciisquid","location":"Lavaland Wastes","health":-100,"typepath":"/mob/living/brain"},"2":{"name":"space carp","ckey":"brhunter45","location":"Starboard Bow Maintenance","health":0,"typepath":"/mob/living/simple_animal/hostile/carp"}},"npcs":{"ash drake":1,"blood-drunk miner":1,"bubblegum":1,"butterfly":8,"Cleanbot":2,"Inactive Camera Eye":1,"Cat Surgeon":1,"Mega Space Carp":2,"grey baby slime (123)":34,"creature":1,"ghost":2,"goldgrub":6,"goliath":36,"gubbuck":1,"guthen":1,"hierophant":1,"hivebot":86,"Unknown":14,"Legion":1,"legion":17,"Lizard":1,"monkey":23,"necropolis tendril":8,"necropolis tendril nest":1,"Mysterious Medibot":1,"Officer Pingsky":1,"Poly":1,"Officer Beep O'sky":1,"Runtime":1,"space carp":68,"space cat":1,"strong hivebot":19,"Syndicate Operative":6,"Syndicate Commando":1,"watcher":17}},"ghosts":{"name":"space carp","ckey":"brhunter45"},"additional data":{"station integrity":61.6}}
